TikTalk/__init__.py
TikTalk/capture copy 2.py
TikTalk/capture.py
TikTalk/config.ini
TikTalk/gpt4o.py
tiktalk-0.1.1.dist-info/METADATA
tiktalk-0.1.1.dist-info/WHEEL
tiktalk-0.1.1.dist-info/entry_points.txt
tiktalk-0.1.1.dist-info/top_level.txt
tiktalk-0.1.1.dist-info/RECORD
