Metadata-Version: 2.1
Name: tiktalk
Version: 0.1.1
Summary: A sophisticated desktop application for capturing and analyzing live captions with AI assistance
Home-page: https://github.com/JimEverest/TikTalk
Author: JimEverest
Author-email: your.email@example.com
Classifier: Development Status :: 3 - Alpha
Classifier: Intended Audience :: End Users/Desktop
Classifier: Topic :: Office/Business :: Office Suites
Classifier: Programming Language :: Python :: 3
Classifier: Programming Language :: Python :: 3.8
Classifier: Programming Language :: Python :: 3.9
Classifier: Programming Language :: Python :: 3.10
Classifier: Programming Language :: Python :: 3.11
Classifier: License :: OSI Approved :: MIT License
Classifier: Operating System :: Microsoft :: Windows
Requires-Python: >=3.8
Requires-Dist: uiautomation>=2.0.20
Requires-Dist: pyperclip>=1.8.2
Requires-Dist: tkhtmlview>=0.1.0
Requires-Dist: markdown>=3.4.0
Requires-Dist: pywin32>=305
Requires-Dist: tkinterweb>=3.23.4
Requires-Dist: configparser>=5.0.0
Requires-Dist: requests>=2.25.0
